magtense/__init__.py
magtense/halbach.py
magtense/magstatics.py
magtense/micromag.py
magtense/utils.py
magtense/lib/__init__.py
magtense/lib/magtensesource.cp313-win_amd64.pyd
magtense/mat/Fe_mur_100_Ms_2_1.csv
magtense/mat/Fe_mur_20_Ms_2_1.csv
magtense/mat/Fe_mur_4000_Ms_2_1.csv
magtense/mat/README.md
magtense/mat/__init__.py
magtense/mat/data_stateFcn.csv
magtense-2.2.5.dist-info/licenses/LICENSE
magtense-2.2.5.dist-info/METADATA
magtense-2.2.5.dist-info/WHEEL
magtense-2.2.5.dist-info/top_level.txt
magtense-2.2.5.dist-info/RECORD
