Metadata-Version: 2.4
Name: magtense
Version: 2.2.5
Summary: MagTense - a micromagnetism and magnetostatic framework
Author-email: Stefan Pollok <spol@dtu.dk>
License-Expression: GPL-3.0-or-later
Project-URL: Homepage, https://www.magtense.org/
Project-URL: Source, https://github.com/cmt-dtu-energy/MagTense
Project-URL: Documentation, https://cmt-dtu-energy.github.io/MagTense/
Keywords: Micromagnetism,Magnetostatics,Demagnetization tensor
Classifier: Development Status :: 3 - Alpha
Classifier: Programming Language :: Python :: 3
Classifier: Programming Language :: Python :: 3.12
Classifier: Programming Language :: Python :: 3.13
Classifier: Topic :: Scientific/Engineering
Requires-Python: >=3.12
License-File: LICENSE
Requires-Dist: h5py>=3.14.0
Requires-Dist: importlib_resources>=6.5.2
Requires-Dist: intel-fortran-rt==2025.2.0
Requires-Dist: matplotlib>=3.10.5
Requires-Dist: mkl==2025.2.0
Requires-Dist: notebook>=7.4.5
Requires-Dist: numpy==2.3.2
Requires-Dist: nvidia-cublas-cu12==12.*
Requires-Dist: nvidia-cuda-runtime-cu12==12.*
Requires-Dist: nvidia-cusparse-cu12==12.*
Requires-Dist: nvidia-nvjitlink-cu12==12.*
Requires-Dist: tqdm>=4.67.1
Dynamic: license-file
